MANIFEST.in
README
setup.py
awsjuju/__init__.py
awsjuju/common.py
awsjuju/controller.py
awsjuju/init.py
awsjuju/lock.py
awsjuju/models.py
awsjuju/unit.py
awsjuju/utils.py
awsjuju.egg-info/PKG-INFO
awsjuju.egg-info/SOURCES.txt
awsjuju.egg-info/dependency_links.txt
awsjuju.egg-info/entry_points.txt
awsjuju.egg-info/requires.txt
awsjuju.egg-info/top_level.txt
awsjuju/services/__init__.py
awsjuju/services/dns.py
awsjuju/services/elb.py
awsjuju/services/rds.py
awsjuju/services/snapshot.py
awsjuju/services/tagger.py
awsjuju/tests/__init__.py
awsjuju/tests/common.py
awsjuju/tests/test_dns.py
awsjuju/tests/test_elb.py
awsjuju/tests/test_lock.py
awsjuju/tests/test_rds.py
awsjuju/tests/test_snapshot.py