Metadata-Version: 1.1
Name: awsjuju
Version: 0.0.2
Summary: Framework for AWS resource management
Home-page: http://github/kapilt/awsjuju
Author: Kapil Thangavelu
Author-email: kapil.foss@gmail.com
License: GPL
Platform: UNKNOWN
Classifier: Intended Audience :: Developers
Classifier: Programming Language :: Python
Classifier: Operating System :: OS Independent
